LocalDataStoragePython/__init__.py
LocalDataStoragePython-0.1.dist-info/LICENSE.txt
LocalDataStoragePython-0.1.dist-info/METADATA
LocalDataStoragePython-0.1.dist-info/WHEEL
LocalDataStoragePython-0.1.dist-info/top_level.txt
LocalDataStoragePython-0.1.dist-info/RECORD
