Metadata-Version: 2.1
Name: LocalDataStoragePython
Version: 0.1
Summary: this package creates a file locally in user's device in a easier way
Author: Samar Panchal
Author-email: 123samarpanchal@gmail.com
Classifier: Programming Language :: Python :: 3
Classifier: License :: OSI Approved :: MIT License
Classifier: Operating System :: OS Independent
License-File: LICENSE.txt
